os_image_builder.py
os_image_builder-0.1.5.dist-info/entry_points.txt
os_image_builder-0.1.5.dist-info/WHEEL
os_image_builder-0.1.5.dist-info/METADATA
os_image_builder-0.1.5.dist-info/RECORD
